pca9674/__init__.py
pca9674/digital_inout.py
pca9674/pca9674.py
circuitpython_pca9674-1.0.0.dist-info/LICENSE
circuitpython_pca9674-1.0.0.dist-info/METADATA
circuitpython_pca9674-1.0.0.dist-info/WHEEL
circuitpython_pca9674-1.0.0.dist-info/top_level.txt
circuitpython_pca9674-1.0.0.dist-info/RECORD
