Metadata-Version: 2.1
Name: circuitpython-pca9674
Version: 1.0.0
Author-email: Finn Scheller <23389984+XENONFFM@users.noreply.github.com>
License: MIT
Project-URL: Homepage, https://github.com/XENONFFM/CircuitPython_PCA9674
Keywords: blinka,circuitpython,micropython,pca9674,pca9674a
Classifier: Intended Audience :: Developers
Classifier: Topic :: Software Development :: Libraries
Classifier: Topic :: Software Development :: Embedded Systems
Classifier: Topic :: System :: Hardware
Classifier: License :: OSI Approved :: MIT License
Classifier: Programming Language :: Python :: 3
License-File: LICENSE
Requires-Dist: Adafruit-Blinka
Requires-Dist: adafruit-circuitpython-busdevice
Provides-Extra: optional
